embex/__init__.py
embex/embex.abi3.so
embex/py.typed
embex-0.1.17.dist-info/METADATA
embex-0.1.17.dist-info/WHEEL
embex-0.1.17.dist-info/entry_points.txt
embex-0.1.17.dist-info/RECORD
