Metadata-Version: 2.4
Name: embex
Version: 0.1.17
Classifier: Programming Language :: Rust
Classifier: Programming Language :: Python :: Implementation :: CPython
Classifier: Programming Language :: Python :: Implementation :: PyPy
Requires-Dist: pydantic>=2.0
Requires-Dist: sphinx>=9.1.0 ; extra == 'dev'
Requires-Dist: sphinx-rtd-theme>=1.3 ; extra == 'dev'
Requires-Dist: pytest-asyncio>=1.3.0 ; extra == 'dev'
Provides-Extra: all
Provides-Extra: chroma
Provides-Extra: dev
Provides-Extra: lancedb
Provides-Extra: pgvector
Provides-Extra: pinecone
Provides-Extra: qdrant
Summary: Embex: A Universal Vector Database ORM
Author-email: BridgeRust <hello@kologojosias.com>
Requires-Python: >=3.12
Project-URL: Homepage, https://github.com/bridgerust/bridgerust/tree/main/bindings/python/embex
Project-URL: Issues, https://github.com/bridgerust/bridgerust/issues
Project-URL: Repository, https://github.com/bridgerust/bridgerust/tree/main/bindings/python/embex
